setup.py
PyQNet.egg-info/PKG-INFO
PyQNet.egg-info/SOURCES.txt
PyQNet.egg-info/dependency_links.txt
PyQNet.egg-info/top_level.txt
qnet/__init__.py
qnet/callbacksender.py
qnet/channel.py
qnet/idgenerator.py
qnet/locks.py
qnet/message.py
qnet/messageset.py
qnet/network.py
qnet/package.py
qnet/protocol.py
qnet/pygamesender.py
qnet/reliable.py
qnet/sender.py
qnet/socketnetwork.py
qnet/stateless.py
qnet/statistics.py
qnet/structure.py